LICENSE
MANIFEST.in
README.md
pyproject.toml
requirements.txt
setup.py
invoke_commands/__init__.py
invoke_commands/clean.py
invoke_commands/docs.py
invoke_commands/misc.py
invoke_commands/notebook_runner.py
invoke_commands/release.py
invoke_commands/sonar.py
invoke_commands/test.py
invoke_commands/vars.py
jkg_evaluators/__init__.py
jkg_evaluators/_version.py
jkg_evaluators/input_kwarg_generators.py
jkg_evaluators/util.py
jkg_evaluators.egg-info/PKG-INFO
jkg_evaluators.egg-info/SOURCES.txt
jkg_evaluators.egg-info/dependency_links.txt
jkg_evaluators.egg-info/requires.txt
jkg_evaluators.egg-info/top_level.txt
jkg_evaluators/assigners/__init__.py
jkg_evaluators/assigners/reassign_separated_minors.py
jkg_evaluators/assigners/separate_minors.py
jkg_evaluators/challenges/__init__.py
jkg_evaluators/challenges/dragonfind.py
jkg_evaluators/challenges/egg.py
jkg_evaluators/challenges/minors.py
jkg_evaluators/challenges/data/__init__.py
jkg_evaluators/challenges/data/comparator_class.py
jkg_evaluators/challenges/data/hotels.py
jkg_evaluators/core/__init__.py
jkg_evaluators/core/core_classes.py